simple_alu.v
module simple_alu(
    input reg        clk,
    input reg        en_i,
    input reg        en_o,
    input wire [1:0] select_op,
    input wire [3:0] a,
    input wire [3:0] b,

    output reg [3:0] out );

    localparam [1:0]
        ADD  = 2'b00,
        AND  = 2'b01,
        OR   = 2'b10,
        NAND = 2'b11;

        //input registers
    reg [3:0] in_a; 
    reg [3:0] in_b;

    reg [3:0] temp;

//sample the inputs when en_i is asserted
    always@(posedge clk)
        begin
            if (en_i) 
                begin
                    in_a <= a;
                    in_b <= b;
                end
            else 
                begin
                    in_a <= in_a;
                    in_b <= in_b;
                end

            if (en_o) 
                begin
                    out <= temp;
                end
            else 
                begin
                    out <='0;
                end
    end
// ALU
    always@(*)
        begin
            case(select_op)
                ADD:  temp = in_a + in_b;
                AND:  temp = in_a & in_b;
                OR:   temp = in_a | in_b;
                NAND: temp = ~(in_a & in_b); 
            endcase
    end

endmodule

tb.sv
`include "simple_alu.v"
module tb_alu();

    logic clk;
    logic en_i;
    logic en_o;
    logic [1:0] select_op;
    logic [3:0] a;
    logic [3:0] b;

    logic [3:0] out;


    simple_alu DUT (
    	.clk       (clk       ),
        .en_i      (en_i      ),
        .en_o      (en_o      ),
        .select_op (select_op ),
        .a         (a         ),
        .b         (b         ),
        .out       (out       )
    );
    
    initial begin
        clk = 0;
        forever #10 clk = ~clk;
    end

    initial begin
        $dumpvars();
        $dumpfile("alu_wave.vcd");
    end

    initial begin
        en_i        = '0;
        en_o        = '0;
        select_op   = '0;
        a           = '0;
        b           = '0;
        repeat(5)@(posedge clk);
        en_i        = 1'b0;
        en_o        = '0;
        select_op   = 2'b00;
        a           = 4'b0001;
        b           = 4'b0011;
        @(posedge clk);

        en_i        = 1'b1;
        en_o        = '0;
        select_op   = 2'b00;
        a           = 4'b0001;
        b           = 4'b0011;
        @(posedge clk);

        en_i        = 1'b0;
        en_o        = 1'b1;
        select_op   = 2'b00;
        a           = 4'b0011;
        b           = 4'b0010;
        @(posedge clk);


        en_i        = 1'b1;
        en_o        = 1'b1;
        select_op   = 2'b01;
        a           = 4'b0011;
        b           = 4'b0010;
        @(posedge clk);

        en_i        = 1'b1;
        en_o        = 1'b1;
        select_op   = 2'b10;
        a           = 4'b0011;
        b           = 4'b0011;
        @(posedge clk);
        repeat(50)@(posedge clk);
        $finish;

    end
endmodule

alu_wave.vcd
$date
	Wed Jul 28 16:24:55 2021
$end

$version
	Synopsys VCS version O-2018.09-SP2-4_Full64
$end

$timescale
	1s
$end

$comment Csum: 1 b3f6f7826fa3d33c $end


$scope module tb_alu $end
$var reg 1 ! clk $end
$var reg 1 " en_i $end
$var reg 1 # en_o $end
$var reg 2 $ select_op [1:0] $end
$var reg 4 % a [3:0] $end
$var reg 4 & b [3:0] $end
$var reg 4 ' out [3:0] $end

$scope module DUT $end
$var reg 1 ! clk $end
$var reg 1 " en_i $end
$var reg 1 # en_o $end
$var wire 2 $ select_op [1:0] $end
$var wire 4 % a [3:0] $end
$var wire 4 & b [3:0] $end
$var reg 4 ' out [3:0] $end
$var reg 4 ( in_a [3:0] $end
$var reg 4 ) in_b [3:0] $end
$var reg 4 * temp [3:0] $end
$upscope $end

$upscope $end

$enddefinitions $end

#0
$dumpvars
0!
0"
0#
b0000 %
b0000 &
bxxxx (
bxxxx )
bxxxx '
b00 $
bxxxx *
$end
#10
1!
b0000 '
#20
0!
#30
1!
#40
0!
#50
1!
#60
0!
#70
1!
#80
0!
#90
1!
b0001 %
b0011 &
#100
0!
#110
1!
1"
b0001 (
b0011 )
b0100 *
#120
0!
#130
1!
0"
1#
b0011 %
b0010 &
b0100 '
#140
0!
#150
1!
1"
b01 $
b0001 *
b0011 (
b0010 )
b0010 *
#160
0!
#170
1!
b10 $
b0011 &
b0011 *
b0011 )
b0010 '
#180
0!
#190
1!
b0011 '
